{"iat":1687109922,"exp":1687110522,"accountId":"http://localhost:3000/yotam-melio/profile/card#me","authTime":1687069142,"codeChallenge":"fM0NshIjT2chET_wSz1nodO0hJoJMAnUUXc4Vd4xo1Q","codeChallengeMethod":"S256","grantId":"fSAsBWMLn2_ymHjl-KFxrT7f7km59BnyfnTWlyQV0IR","redirectUri":"https://penny.vincenttunru.com/explore/","resource":"http://example.com/","scope":"openid webid","sessionUid":"Wqd4QFi6-XIXB-vn4CXT2","kind":"AuthorizationCode","jti":"cLQDX_G-4BPpbJ4FFkfvzuTcy-1ib1PkOhcqkaDKvQF","clientId":"-r_TKgZaQOPkS93AqZ3y2","expiresWithSession":true,"consumed":1687109922}